mergedeep/__init__.py
mergedeep/mergedeep.py
mergedeep/test_mergedeep.py
runch_mergedeep-1.3.5.dist-info/LICENSE
runch_mergedeep-1.3.5.dist-info/METADATA
runch_mergedeep-1.3.5.dist-info/WHEEL
runch_mergedeep-1.3.5.dist-info/top_level.txt
runch_mergedeep-1.3.5.dist-info/RECORD
