Metadata-Version: 2.1
Name: runch-mergedeep
Version: 1.3.5
Summary: A deep merge function for 🐍.
Home-page: https://github.com/XieJiSS/mergedeep
Author: Travis Clarke
Author-email: travis.m.clarke@gmail.com
Maintainer: XieJiSS
Maintainer-email: panrz@deepseek.com
Classifier: Programming Language :: Python :: 3
Classifier: Programming Language :: Python :: 3.10
Classifier: Programming Language :: Python :: 3.11
Classifier: Programming Language :: Python :: 3.12
Classifier: Programming Language :: Python :: 3.13
Classifier: License :: OSI Approved :: MIT License
Classifier: Operating System :: OS Independent
Requires-Python: >=3.10
License-File: LICENSE
